CONTRIBUTING.md
LICENSE
ananke/__init__.py
ananke/datasets/__init__.py
ananke/datasets/helpers.py
ananke/datasets/real/evans_richardson_wisconsin.csv
ananke/datasets/simulated/__init__.py
ananke/datasets/simulated/a_fixable.csv
ananke/datasets/simulated/conditionally_ignorable.csv
ananke/datasets/simulated/frontdoor.csv
ananke/discovery/__init__.py
ananke/estimation/__init__.py
ananke/estimation/automated_if.py
ananke/estimation/counterfactual_mean.py
ananke/estimation/empirical_plugin.py
ananke/factors/__init__.py
ananke/factors/discrete_factor.py
ananke/graphs/__init__.py
ananke/graphs/admg.py
ananke/graphs/bg.py
ananke/graphs/cg.py
ananke/graphs/dag.py
ananke/graphs/graph.py
ananke/graphs/ig.py
ananke/graphs/missing_admg.py
ananke/graphs/sg.py
ananke/graphs/ug.py
ananke/graphs/vertex.py
ananke/identification/__init__.py
ananke/identification/missing_id.py
ananke/identification/one_line.py
ananke/identification/opt_adjust.py
ananke/identification/oracle.py
ananke/inference/__init__.py
ananke/inference/variable_elimination.py
ananke/models/__init__.py
ananke/models/bayesian_network.py
ananke/models/binary_nested.py
ananke/models/fixtures.py
ananke/models/linear_gaussian_sem.py
ananke/utils.py
ananke_causal-0.4.0.dist-info/LICENSE
ananke_causal-0.4.0.dist-info/METADATA
ananke_causal-0.4.0.dist-info/WHEEL
ananke_causal-0.4.0.dist-info/RECORD
