Metadata-Version: 2.1
Name: ananke-causal
Version: 0.4.0
Summary: Ananke, named for the Greek primordial goddess of necessity and causality, is a python package for causal inference using the language of graphical models.
Home-page: https://gitlab.com/causal/ananke
License: Apache 2.0
Author: Ananke community
Author-email: rbhatta8@jhu.edu
Requires-Python: >=3.9,<4.0
Classifier: Development Status :: 4 - Beta
Classifier: License :: OSI Approved :: Apache Software License
Classifier: License :: Other/Proprietary License
Classifier: Programming Language :: Python :: 3
Classifier: Programming Language :: Python :: 3.9
Classifier: Programming Language :: Python :: 3.10
Classifier: Programming Language :: Python :: 3.11
Classifier: Programming Language :: Python :: 3.8
Provides-Extra: opt
Provides-Extra: viz
Requires-Dist: graphviz (>=0.20.1,<0.21.0) ; extra == "viz"
Requires-Dist: jax (>=0.4.8,<0.5.0)
Requires-Dist: jaxlib (>=0.4.7,<0.5.0)
Requires-Dist: matplotlib (>=3.8.0,<4.0.0)
Requires-Dist: mystic (>=0.4.0,<0.5.0)
Requires-Dist: numpy (>=1.23.0,<2.0.0)
Requires-Dist: pandas (>=1.4.3,<2.0.0)
Requires-Dist: pgmpy (>=0.1.21,<0.2.0)
Requires-Dist: pygraphviz ; extra == "viz"
Requires-Dist: scipy (>=1.8.1,<2.0.0)
Requires-Dist: statsmodels (>=0.13.2,<0.14.0)
Requires-Dist: torch (>=2.0.0,<3.0.0,!=2.0.1,!=2.1.0) ; extra == "opt"
Project-URL: Documentation, https://ananke.readthedocs.io/en/latest/index.html
Project-URL: Repository, https://gitlab.com/causal/ananke
